liquidcrystal_i2c/__init__.py
liquidcrystal_i2c/liquidcrystal_i2c.py
liquidcrystal_i2c_linux-1.0.0.dist-info/LICENSE
liquidcrystal_i2c_linux-1.0.0.dist-info/METADATA
liquidcrystal_i2c_linux-1.0.0.dist-info/WHEEL
liquidcrystal_i2c_linux-1.0.0.dist-info/top_level.txt
liquidcrystal_i2c_linux-1.0.0.dist-info/RECORD
