Metadata-Version: 2.1
Name: liquidcrystal-i2c-linux
Version: 1.0.0
Summary: Python port of the LiquidCrystal_I2C C++ library for Hitachi HD44780
Home-page: https://github.com/a13ssandr0/liquidcrystal_i2c-linux
Author: Alessandro Campolo
Author-email: campoloalex@gmail.com
License: UNKNOWN
Project-URL: Bug Tracker, https://github.com/a13ssandr0/liquidcrystal_i2c-linux/issues
Platform: UNKNOWN
Classifier: Programming Language :: Python :: 3
Classifier: License :: OSI Approved :: MIT License
Classifier: Operating System :: POSIX :: Linux
License-File: LICENSE
Requires-Dist: smbus
